{
  "meta": {
    "title": "大件运输法规知识库",
    "description": "超限运输车辆行驶公路管理规定及相关法规的结构化知识库",
    "version": "1.0",
    "base_regulation": "超限运输车辆行驶公路管理规定（交通运输部令2021年第12号）",
    "effective_date": "2021-08-11"
  },
  "articles": [
    {
      "article_number": "3",
      "title": "超限认定标准",
      "content": "有下列情形之一的公路货物运输车辆，属于超限运输车辆：（一）车货总高度从地面算起超过4米；（二）车货总宽度超过2.55米；（三）车货总长度超过18.1米；（四）二轴货车，其车货总质量超过18000千克；（五）三轴货车，其车货总质量超过25000千克；三轴汽车列车，其车货总质量超过27000千克；（六）四轴货车，其车货总质量超过31000千克；四轴汽车列车，其车货总质量超过36000千克；（七）五轴汽车列车，其车货总质量超过43000千克；（八）六轴及六轴以上汽车列车，其车货总质量超过49000千克。",
      "tags": ["超限标准", "尺寸限制", "重量限制", "认定", "轴数"],
      "related_classes": ["I", "II", "III"],
      "details": {
        "height_limit_m": 4.0,
        "width_limit_m": 2.55,
        "length_limit_m": 18.1,
        "weight_limits_by_axle": {
          "2": 18,
          "3": 25,
          "3_train": 27,
          "4": 31,
          "4_train": 36,
          "5_train": 43,
          "6_plus": 49
        }
      }
    },
    {
      "article_number": "6",
      "title": "许可申请材料",
      "content": "申请公路超限运输许可的，承运人应当向公路管理机构提交下列材料：（一）公路超限运输申请表，主要内容包括货物名称、外廓尺寸和质量，运输起讫点、通行路线和行驶时间，车辆号牌、轴数、轴距和轮胎数；（二）承运人的道路运输经营许可证，经办人的身份证件和授权委托书；（三）车辆行驶证或者临时行驶车号牌；（四）车货总体外廓尺寸轮廓图和护送方案。其中，护送方案应当包含护送车辆配置方案、护送人员配备方案、护送路线情况说明、护送操作细则、异常情况处理预案等内容。申请III类大件运输许可的，应当同时提交记录载货时车货实际尺寸和重量的称重检测信息。",
      "tags": ["申请材料", "许可", "申请表", "证件", "护送方案", "III类"],
      "related_classes": ["I", "II", "III"],
      "required_documents": {
        "all": ["公路超限运输申请表", "道路运输经营许可证", "经办人身份证件", "授权委托书", "车辆行驶证或临时号牌", "车货总体外廓尺寸轮廓图"],
        "I": ["公路超限运输申请表", "道路运输经营许可证", "经办人身份证件", "授权委托书", "车辆行驶证或临时号牌"],
        "II": ["公路超限运输申请表", "道路运输经营许可证", "经办人身份证件", "授权委托书", "车辆行驶证或临时号牌", "车货总体外廓尺寸轮廓图", "护送方案"],
        "III": ["公路超限运输申请表", "道路运输经营许可证", "经办人身份证件", "授权委托书", "车辆行驶证或临时号牌", "车货总体外廓尺寸轮廓图", "护送方案（含护送车辆配置方案、护送人员配备方案、护送路线说明、操作细则、异常处理预案）", "载货时车货实际尺寸和重量的称重检测信息"]
      }
    },
    {
      "article_number": "8",
      "title": "许可审批机关",
      "content": "跨省、自治区、直辖市进行超限运输的，向起运地省级公路管理机构申请，由起运地省级公路管理机构受理并统一组织协调沿线省级公路管理机构联合审批。在省、自治区范围内进行超限运输的，向省级公路管理机构提出申请。公路管理机构对申请材料进行审查，需要对车货实际尺寸和质量进行复核的，应当在5个工作日内进行复核。",
      "tags": ["审批", "许可机关", "省级公路管理机构", "跨省", "联合审批"],
      "related_classes": ["I", "II", "III"],
      "authority": "省级公路管理机构（省交通运输厅公路局）"
    },
    {
      "article_number": "10",
      "title": "许可办理时限",
      "content": "公路管理机构审批公路超限运输申请，应当根据超限运输的情形，在下列期限内作出行政许可决定：（一）一类大件运输：即时办理；（二）二类大件运输：自受理申请之日起2个工作日内作出；（三）三类大件运输：自受理申请之日起5个工作日内作出。需要采取加固、改造措施以及需要进行现场勘验的，所需时间不计算在前款规定的期限内。",
      "tags": ["办理时限", "审批时间", "即时办理", "工作日"],
      "related_classes": ["I", "II", "III"],
      "time_limits": {
        "I": {"days": 0, "description": "即时办理"},
        "II": {"days": 2, "description": "2个工作日"},
        "III": {"days": 5, "description": "5个工作日"}
      }
    },
    {
      "article_number": "11",
      "title": "许可证有效期",
      "content": "超限运输车辆通行证的有效期按照下列规定执行：（一）一类大件运输：6个月；（二）二类大件运输：3个月；（三）三类大件运输：1个月，或者按照实际运输路线和时限确定。通行证有效期届满前，可以申请续期，但最长不得超过原有效期。",
      "tags": ["有效期", "许可证", "通行证", "期限", "续期"],
      "related_classes": ["I", "II", "III"],
      "validity": {
        "I": {"months": 6, "description": "6个月"},
        "II": {"months": 3, "description": "3个月"},
        "III": {"months": 1, "description": "1个月或按单次运输确定"}
      }
    },
    {
      "article_number": "22",
      "title": "III类大件运输护送要求",
      "content": "三类大件运输车辆行驶公路的，承运人应当按照护送方案组织护送。护送车辆应当配备明显的警示标志，行驶过程中应当开启危险报警闪光灯。护送方案应当根据车货实际尺寸、质量和通行路线情况制定，确保运输安全。III类大件运输承运人应当按照要求配备护送车辆和护送人员。",
      "tags": ["护送", "III类", "护送方案", "警示标志", "安全"],
      "related_classes": ["III"],
      "escort_required": true
    },
    {
      "article_number": "43",
      "title": "超限运输处罚标准",
      "content": "车辆违法超限运输的，由公路管理机构根据违法行为的性质、情节和危害程度，按下列标准给予处罚：（一）车货总高度从地面算起超过4米、总宽度超过2.55米或者总长度超过18.1米的，处200元以上1000元以下罚款；情节严重的，处1000元以上3000元以下罚款。（二）车货总质量超过限定标准，但未超过1000千克的，予以警告；超过1000千克的，每超1000千克罚款500元，最高不得超过30000元。有前款所列多项违法行为的，相应违法行为的罚款数额应当累计，但累计罚款数额最高不得超过30000元。",
      "tags": ["处罚", "罚款", "超限", "尺寸", "重量", "法律责任"],
      "related_classes": ["I", "II", "III"],
      "penalties": {
        "size": {"min": 200, "max": 3000, "description": "尺寸超限罚款200-3000元"},
        "weight": {"base": 500, "per_1000kg": 500, "max": 30000, "description": "重量超限每超1000kg罚款500元，最高30000元"},
        "combined_max": 30000
      }
    },
    {
      "article_number": "classification",
      "title": "大件运输许可三类分类标准",
      "content": "大件运输按照车货总质量、外廓尺寸分为三类：（一）一类大件运输：车货总高度不超过4.5米，总宽度不超过3.75米，总长度不超过28米，且车货总质量不超过100吨；（二）二类大件运输：车货总高度、总宽度、总长度不超过一类标准，但车货总质量超过100吨；（三）三类大件运输：车货总高度超过4.5米，或总宽度超过3.75米，或总长度超过28米。",
      "tags": ["分类标准", "一类", "二类", "三类", "尺寸", "重量"],
      "related_classes": ["I", "II", "III"],
      "classification_thresholds": {
        "I": {"height_m": 4.5, "width_m": 3.75, "length_m": 28, "weight_t": 100},
        "II": {"height_m": 4.5, "width_m": 3.75, "length_m": 28, "weight_gt_t": 100},
        "III": {"height_gt_m": 4.5, "width_gt_m": 3.75, "length_gt_m": 28}
      }
    },
    {
      "article_number": "escort_guide",
      "title": "护送车辆与警车护送规范",
      "content": "护送车辆配置标准：根据车辆外廓尺寸和通行路线情况确定护送车辆数量。（1）车货总宽度在3.75米至4.5米之间的，配备不少于1辆护送车辆；超过4.5米的，配备不少于2辆护送车辆。（2）车货总长度在28米至35米之间的，配备不少于1辆护送车辆；超过35米的，配备不少于2辆护送车辆。（3）车货总高度在4.5米至5.0米之间的，配备不少于1辆护送车辆；超过5.0米的，配备不少于2辆护送车辆。需要交通管理部门警车护送的，由公路管理机构商请公安机关交通管理部门决定。",
      "tags": ["护送", "护送车辆", "警车", "护送标准", "配置", "III类"],
      "related_classes": ["III"],
      "escort_vehicle_requirements": {
        "width": [
          {"min": 3.75, "max": 4.5, "vehicles": 1},
          {"min": 4.5, "max": 99, "vehicles": 2}
        ],
        "length": [
          {"min": 28, "max": 35, "vehicles": 1},
          {"min": 35, "max": 99, "vehicles": 2}
        ],
        "height": [
          {"min": 4.5, "max": 5.0, "vehicles": 1},
          {"min": 5.0, "max": 99, "vehicles": 2}
        ],
        "police_escort_thresholds": {
          "description": "宽度超过4.5米或长度超过35米或高度超过5.0米，由公路管理机构商请公安机关交通管理部门决定是否警车护送",
          "width_m": 4.5,
          "length_m": 35,
          "height_m": 5.0
        }
      }
    }
  ]
}
